nginr/__init__.py
nginr/main.py
nginr-0.1.8.dist-info/licenses/LICENSE
nginr-0.1.8.dist-info/METADATA
nginr-0.1.8.dist-info/WHEEL
nginr-0.1.8.dist-info/entry_points.txt
nginr-0.1.8.dist-info/top_level.txt
nginr-0.1.8.dist-info/RECORD
